aiolibs_executor/__init__.py
aiolibs_executor/_executor.py
aiolibs_executor/py.typed
aiolibs_executor-0.0.0.dist-info/LICENSE
aiolibs_executor-0.0.0.dist-info/METADATA
aiolibs_executor-0.0.0.dist-info/WHEEL
aiolibs_executor-0.0.0.dist-info/RECORD
