Metadata-Version: 2.3
Name: aiolibs-executor
Version: 0.0.0
Summary: Asyncio version of concurrent.futures.Executor
Author: Andrew Svetlov
Author-email: andrew.svetlov@gmail.com
Requires-Python: >=3.13
Classifier: Programming Language :: Python :: 3
Classifier: Programming Language :: Python :: 3.13
